c11204ps/__about__.py
c11204ps/__init__.py
c11204ps-0.2.1.dist-info/METADATA
c11204ps-0.2.1.dist-info/WHEEL
c11204ps-0.2.1.dist-info/licenses/LICENSE.txt
c11204ps-0.2.1.dist-info/RECORD
