Metadata-Version: 2.1
Name: c11204ps
Version: 0.2.1
Summary: Python package for controlling a Hamamatsu c11204-01/02 power supply.
Project-URL: Documentation, https://github.com/burbschat/c11204ps#readme
Project-URL: Issues, https://github.com/burbschat/c11204ps/issues
Project-URL: Source, https://github.com/burbschat/c11204ps
Author-email: burbschat <b.urbschat@tum.de>
License-Expression: GPL-3.0-only
License-File: LICENSE.txt
Keywords: c11204,c11204-01,c11204-02,hamamatsu,power supply
Classifier: Development Status :: 4 - Beta
Classifier: Programming Language :: Python
Classifier: Programming Language :: Python :: 3.7
Classifier: Programming Language :: Python :: 3.8
Classifier: Programming Language :: Python :: 3.9
Classifier: Programming Language :: Python :: 3.10
Classifier: Programming Language :: Python :: 3.11
Classifier: Programming Language :: Python :: Implementation :: CPython
Classifier: Programming Language :: Python :: Implementation :: PyPy
Requires-Python: >=3.7
Requires-Dist: pyserial
